{"users":[{"id":74091284,"firstName":"veniam dolore amet laboris","lastName":"aliqua Duis occaecat ex adipisicing","email":"mxBOi2m0-wr4tvb@gONvEVqm.lolf"},{"id":49315680,"firstName":"labore Lorem laborum in","lastName":"sit","email":"lEZuckLzhMK@KUbzjVIokGJAzKqDHsFCfnUaTAQYMgikQ.qkwd"},{"id":13909502,"firstName":"labore nostrud","lastName":"commodo volu","email":"Cjg0akGQ@LhfNxkMvNKpBJbxratc.oiz"},{"id":25882097,"firstName":"deserunt","lastName":"aliqua reprehenderit voluptate sunt","email":"YEGKX@gpylFJvkRAFOLQ.dn"}]}